tal/.tal.conf.example
tal/__init__.py
tal/__main__.py
tal/callbacks.py
tal/config.py
tal/enums.py
tal/log.py
tal/util.py
tal/io/__init__.py
tal/io/capture_data.py
tal/io/format.py
tal/plot/__init__.py
tal/plot/compare.py
tal/plot/plotter3d.py
tal/plot/xy.py
tal/reconstruct/__init__.py
tal/reconstruct/filters.py
tal/reconstruct/util.py
tal/reconstruct/bp/__init__.py
tal/reconstruct/bp/backprojection.py
tal/reconstruct/fbp/__init__.py
tal/reconstruct/fk/__init__.py
tal/reconstruct/pf/__init__.py
tal/reconstruct/pf/pf_solver.py
tal/reconstruct/pf/phasor_fields.py
tal/reconstruct/pf/propagator.py
tal/reconstruct/pf/rsd_kernel.py
tal/reconstruct/pf_dev/__init__.py
tal/reconstruct/pf_dev/phasor_fields.py
tal/reconstruct/upf_dev/__init__.py
tal/reconstruct/upf_dev/phasor_fields.py
tal/render/__init__.py
tal/render/create.py
tal/render/mitsuba2_transient_nlos.py
tal/render/mitsuba3_transient_nlos.py
tal/render/render.py
tal/render/scene_defaults.yaml
tal/render/util.py
y_tal-0.20.0.dist-info/LICENSE
y_tal-0.20.0.dist-info/METADATA
y_tal-0.20.0.dist-info/WHEEL
y_tal-0.20.0.dist-info/entry_points.txt
y_tal-0.20.0.dist-info/top_level.txt
y_tal-0.20.0.dist-info/RECORD
