Metadata-Version: 2.1
Name: y-tal
Version: 0.20.0
Summary: (Your) Transient Auxiliary Library - Analysis and processing of time-resolved light transport
Home-page: https://github.com/diegoroyo/tal
Author: Diego Royo & Pablo Luesia
Author-email: droyo@unizar.es
Classifier: Programming Language :: Python :: 3
Classifier: License :: OSI Approved :: GNU General Public License v3 (GPLv3)
Classifier: Operating System :: OS Independent
Requires-Python: >=3.8
License-File: LICENSE
Requires-Dist: dill (>=0.3.6)
Requires-Dist: h5py (>=3.8.0)
Requires-Dist: imageio (==2.25.1)
Requires-Dist: Pillow (==10.3.0)
Requires-Dist: matplotlib (>=3.7.0)
Requires-Dist: nptyping (>=2.5.0)
Requires-Dist: numpy (>=1.24.2)
Requires-Dist: numba (>=0.54.1)
Requires-Dist: PyYAML (>=6.0)
Requires-Dist: scipy (>=1.15.2)
Requires-Dist: setuptools (>=67.3.3)
Requires-Dist: tqdm (>=4.64.1)
Requires-Dist: pyvista (>=0.38.2)
Requires-Dist: psutil (>=5.9.8)
